kotoba/__init__.py
kotoba/common.py
kotoba/driver.py
kotoba/exception.py
kotoba/fs.py
kotoba/graph.py
kotoba/kami.py
kotoba/kotoba.py
kotoba/misc.py
kotoba/parser.py
kotoba/selector.py
kotoba-3.1.2.dist-info/licenses/LICENSE
kotoba-3.1.2.dist-info/METADATA
kotoba-3.1.2.dist-info/WHEEL
kotoba-3.1.2.dist-info/top_level.txt
kotoba-3.1.2.dist-info/RECORD
