Metadata-Version: 2.4
Name: kotoba
Version: 3.1.2
Summary: XML/JSON Reading Library with Level-3 CSS Selector
Requires-Python: >=3.9
License-File: LICENSE
Provides-Extra: build
Requires-Dist: setuptools; extra == "build"
Dynamic: license-file
